{
  "dependencies": {
    "secrets1": {
      "type": "secrets.user"
    },
    "mssql1": {
      "serviceConnectorResourceId": "/subscriptions/[parameters('subscriptionId')]/resourceGroups/[parameters('serviceConnectorResourceGroupName')]/providers/Microsoft.ServiceLinker/locations/brazilsouth/connectors/ConnectionStringsDatabaseConnection_FC05FC75F8",
      "secretStore": "LocalSecretsFile",
      "resourceId": "/subscriptions/[parameters('subscriptionId')]/resourceGroups/[parameters('resourceGroupName')]/providers/Microsoft.Sql/servers/eagenda-backend-2025-caue/databases/eAgendaBd",
      "type": "mssql.azure",
      "connectionId": "ConnectionStrings:DatabaseConnection"
    }
  }
}